pythonic_gmail/__init__.py
pythonic_gmail/_version.py
pythonic_gmail/api.py
pythonic_gmail/batch.py
pythonic_gmail/client.py
pythonic_gmail/client_builder.py
pythonic_gmail/custom_model.py
pythonic_gmail/iterator.py
pythonic_gmail/lazy_imports.py
pythonic_gmail/model.py
pythonic_gmail/paginate.py
pythonic_gmail/paths.py
pythonic_gmail/type_hint.py
pythonic_gmail/utils.py
pythonic_gmail/vendor/__init__.py
pythonic_gmail/vendor/pytest_cov_helper.py
pythonic_gmail-0.1.3.dist-info/AUTHORS.rst
pythonic_gmail-0.1.3.dist-info/LICENSE.txt
pythonic_gmail-0.1.3.dist-info/METADATA
pythonic_gmail-0.1.3.dist-info/WHEEL
pythonic_gmail-0.1.3.dist-info/RECORD
