Metadata-Version: 2.3
Name: pythonic_gmail
Version: 0.1.3
Summary: An example project generated by cookiecutter-pywf_open_source.
License: MIT
Author: Sanhe Hu
Author-email: husanhe@email.com
Maintainer: Sanhe Hu
Maintainer-email: husanhe@email.com
Requires-Python: >=3.10,<4.0
Classifier: License :: OSI Approved :: MIT License
Classifier: Programming Language :: Python :: 3
Classifier: Programming Language :: Python :: 3.10
Classifier: Programming Language :: Python :: 3.11
Classifier: Programming Language :: Python :: 3.12
Classifier: Programming Language :: Python :: 3.13
Provides-Extra: auto
Provides-Extra: dev
Provides-Extra: doc
Provides-Extra: email
Provides-Extra: test
Requires-Dist: Sphinx (>=7.4.7,<8.0.0) ; extra == "doc"
Requires-Dist: beautifulsoup4 (>=4.10.0,<5.0.0) ; extra == "email"
Requires-Dist: build (>=1.2.1,<2.0.0) ; extra == "dev"
Requires-Dist: docfly (==3.0.0) ; extra == "doc"
Requires-Dist: enum-mate (>=0.1.1,<1.0.0)
Requires-Dist: func-args (>=1.0.1,<2.0.0)
Requires-Dist: furo (==2024.8.6) ; extra == "doc"
Requires-Dist: google-api-python-client (>=2.157.0,<3.0.0)
Requires-Dist: google-api-python-client-stubs (>=1.29.0,<2.0.0) ; extra == "dev"
Requires-Dist: google-auth-httplib2 (>=0.2.0,<1.0.0)
Requires-Dist: google-auth-oauthlib (>=1.2.1,<2.0.0)
Requires-Dist: ipython (>=8.18.1,<8.19.0) ; extra == "doc"
Requires-Dist: iterproxy (>=0.3.1,<1.0.0)
Requires-Dist: more-itertools (>=10.6.0) ; python_version < "3.12"
Requires-Dist: nbsphinx (>=0.8.12,<1.0.0) ; extra == "doc"
Requires-Dist: pygments (>=2.18.0,<3.0.0) ; extra == "doc"
Requires-Dist: pytest (>=8.2.2,<9.0.0) ; extra == "test"
Requires-Dist: pytest-cov (>=6.0.0,<7.0.0) ; extra == "test"
Requires-Dist: rich (>=13.8.1,<14.0.0) ; extra == "dev"
Requires-Dist: rstobj (==1.2.1) ; extra == "doc"
Requires-Dist: simple_aws_ssm_parameter_store (>=0.2.3,<1.0.0) ; extra == "test"
Requires-Dist: soft-deps (>=0.1.1,<1.0.0)
Requires-Dist: sphinx-copybutton (>=0.5.2,<1.0.0) ; extra == "doc"
Requires-Dist: sphinx-design (>=0.6.1,<1.0.0) ; extra == "doc"
Requires-Dist: sphinx-jinja (>=2.0.2,<3.0.0) ; extra == "doc"
Requires-Dist: twine (>=6.0.0,<7.0.0) ; extra == "dev"
Requires-Dist: typing-extensions (>=4.0.0,<5.0.0) ; python_version < "3.11"
Requires-Dist: wheel (>=0.45.0,<1.0.0) ; extra == "dev"
Project-URL: Changelog, https://github.com/MacHu-GWU/pythonic_gmail-project/blob/main/release-history.rst
Project-URL: Documentation, https://pythonic-gmail.readthedocs.io/en/latest/
Project-URL: Download, https://pypi.org/pypi/pythonic-gmail#files
Project-URL: Homepage, https://github.com/MacHu-GWU/pythonic_gmail-project
Project-URL: Issues, https://github.com/MacHu-GWU/pythonic_gmail-project/issues
Project-URL: Repository, https://github.com/MacHu-GWU/pythonic_gmail-project
